trustyai/__init__.py
trustyai/_default_initializer.py
trustyai/initializer.py
trustyai/version.py
trustyai/dep/.gitkeep
trustyai/dep/org/trustyai/.gitkeep
trustyai/dep/org/trustyai/explainability-arrow-999-SNAPSHOT.jar
trustyai/explainers/__init__.py
trustyai/explainers/counterfactuals.py
trustyai/explainers/explanation_results.py
trustyai/explainers/lime.py
trustyai/explainers/pdp.py
trustyai/explainers/shap.py
trustyai/explainers/extras/tsice.py
trustyai/explainers/extras/tslime.py
trustyai/explainers/extras/tssaliency.py
trustyai/language/__init__.py
trustyai/language/detoxify/__init__.py
trustyai/language/detoxify/tmarco.py
trustyai/local/__init__.py
trustyai/metrics/__init__.py
trustyai/metrics/distance.py
trustyai/metrics/language.py
trustyai/metrics/saliency.py
trustyai/metrics/fairness/__init__.py
trustyai/metrics/fairness/group.py
trustyai/model/__init__.py
trustyai/model/domain.py
trustyai/utils/DataUtils.py
trustyai/utils/__init__.py
trustyai/utils/_tyrus_info_text.py
trustyai/utils/_visualisation.py
trustyai/utils/data_conversions.py
trustyai/utils/text.py
trustyai/utils/tokenizers.py
trustyai/utils/tyrus.py
trustyai/utils/api/api.py
trustyai/utils/extras/metrics_service.py
trustyai/utils/extras/models.py
trustyai/utils/extras/timeseries.py
trustyai/visualizations/__init__.py
trustyai/visualizations/distance.py
trustyai/visualizations/lime.py
trustyai/visualizations/pdp.py
trustyai/visualizations/shap.py
trustyai/visualizations/visualization_results.py
trustyai-0.6.2.dist-info/licenses/LICENSE
trustyai-0.6.2.dist-info/METADATA
trustyai-0.6.2.dist-info/WHEEL
trustyai-0.6.2.dist-info/top_level.txt
trustyai-0.6.2.dist-info/RECORD
