Metadata-Version: 2.4
Name: trustyai
Version: 0.6.2
Summary: Python bindings to the TrustyAI explainability library.
Author-email: Rui Vieira <rui@redhat.com>
License: Apache License Version 2.0
Project-URL: homepage, https://github.com/trustyai-explainability/trustyai-explainability-python
Project-URL: documentation, https://trustyai-explainability-python.readthedocs.io/en/latest/
Project-URL: repository, https://github.com/trustyai-explainability/trustyai-explainability-python
Keywords: trustyai,xai,explainability,ml
Classifier: License :: OSI Approved :: Apache Software License
Classifier: Development Status :: 4 - Beta
Classifier: Intended Audience :: Developers
Classifier: Intended Audience :: Science/Research
Classifier: Programming Language :: Java
Classifier: Programming Language :: Python :: 3.10
Classifier: Programming Language :: Python :: 3.11
Classifier: Programming Language :: Python :: 3.12
Classifier: Topic :: Scientific/Engineering :: Artificial Intelligence
Classifier: Topic :: Software Development :: Libraries :: Java Libraries
Requires-Python: >=3.10
License-File: LICENSE
Requires-Dist: Jpype1==1.5.0
Requires-Dist: pyarrow==20.0.0
Requires-Dist: matplotlib~=3.10.3
Requires-Dist: pandas~=1.5.3
Requires-Dist: numpy==1.26.4
Requires-Dist: jupyter-bokeh~=3.0.7
Provides-Extra: dev
Requires-Dist: JPype1==1.5.0; extra == "dev"
Requires-Dist: black~=22.12.0; extra == "dev"
Requires-Dist: click==8.0.4; extra == "dev"
Requires-Dist: joblib~=1.2.0; extra == "dev"
Requires-Dist: jupyterlab~=3.5.3; extra == "dev"
Requires-Dist: numpydoc==1.5.0; extra == "dev"
Requires-Dist: pylint==3.2.0; extra == "dev"
Requires-Dist: pytest~=7.2.1; extra == "dev"
Requires-Dist: pytest-benchmark==4.0.0; extra == "dev"
Requires-Dist: pytest-forked~=1.6.0; extra == "dev"
Requires-Dist: scikit-learn~=1.7.0; extra == "dev"
Requires-Dist: setuptools; extra == "dev"
Requires-Dist: twine==3.4.2; extra == "dev"
Requires-Dist: wheel~=0.38.4; extra == "dev"
Requires-Dist: xgboost~=3.0.2; extra == "dev"
Provides-Extra: extras
Requires-Dist: aix360[default,tsice,tslime,tssaliency]==0.3.0; extra == "extras"
Provides-Extra: detoxify
Requires-Dist: transformers~=4.36.2; extra == "detoxify"
Requires-Dist: datasets; extra == "detoxify"
Requires-Dist: scipy~=1.12.0; extra == "detoxify"
Requires-Dist: torch~=2.2.1; extra == "detoxify"
Requires-Dist: iter-tools; extra == "detoxify"
Requires-Dist: evaluate; extra == "detoxify"
Requires-Dist: trl; extra == "detoxify"
Provides-Extra: api
Requires-Dist: kubernetes; extra == "api"
Dynamic: license-file
